README.md
setup.cfg
setup.py
mst/__init__.py
mst/args.py
mst/cmds.py
mst/ecc.py
mst/mainstay.py
mst/msqr.py
mst/rpchost.py
mst/verify.py
pymainstay.egg-info/PKG-INFO
pymainstay.egg-info/SOURCES.txt
pymainstay.egg-info/dependency_links.txt
pymainstay.egg-info/entry_points.txt
pymainstay.egg-info/requires.txt
pymainstay.egg-info/top_level.txt