Metadata-Version: 2.1
Name: pymainstay
Version: 0.1.1
Summary: Tool to attest state and verify Mainstay sequence proofs
Home-page: https://github.com/commerceblock/pymainstay
Author: CommerceBlock
Author-email: tom@commerceblock.com
License: MIT
Download-URL: https://github.com/commerceblock/pymainstay/archive/0.1.1.tar.gz
Platform: UNKNOWN
Classifier: Development Status :: 3 - Alpha
Classifier: Intended Audience :: Developers
Classifier: Topic :: Security :: Cryptography
Classifier: License :: OSI Approved :: MIT License
Classifier: Programming Language :: Python :: 3 :: Only
